README.md
setup.cfg
setup.py
cashfree_sdk/__init__.py
cashfree_sdk/client.py
cashfree_sdk/verification.py
cashfree_sdk.egg-info/PKG-INFO
cashfree_sdk.egg-info/SOURCES.txt
cashfree_sdk.egg-info/dependency_links.txt
cashfree_sdk.egg-info/not-zip-safe
cashfree_sdk.egg-info/requires.txt
cashfree_sdk.egg-info/top_level.txt
cashfree_sdk/exceptions/__init__.py
cashfree_sdk/exceptions/exceptions.py
cashfree_sdk/payouts/__authorize_creds.py
cashfree_sdk/payouts/__init__.py
cashfree_sdk/payouts/__payouts_config.py
cashfree_sdk/payouts/__payouts_creds.py
cashfree_sdk/payouts/__request.py
cashfree_sdk/payouts/beneficiary/__create_beneficiary.py
cashfree_sdk/payouts/beneficiary/__delete_beneficiary.py
cashfree_sdk/payouts/beneficiary/__get_beneficiary_details.py
cashfree_sdk/payouts/beneficiary/__get_beneficiary_id.py
cashfree_sdk/payouts/beneficiary/__init__.py
cashfree_sdk/payouts/cashgram/__create_cashgram.py
cashfree_sdk/payouts/cashgram/__deactivate_cashgram.py
cashfree_sdk/payouts/cashgram/__get_cashgram_status.py
cashfree_sdk/payouts/cashgram/__init__.py
cashfree_sdk/payouts/transfers/__create_bulk_transfers.py
cashfree_sdk/payouts/transfers/__get_balance.py
cashfree_sdk/payouts/transfers/__get_bulk_transfer_status.py
cashfree_sdk/payouts/transfers/__get_transfer_status.py
cashfree_sdk/payouts/transfers/__init__.py
cashfree_sdk/payouts/transfers/__list_transfers.py
cashfree_sdk/payouts/transfers/__request_transfer.py
cashfree_sdk/payouts/transfers/__self_withdrawal.py
cashfree_sdk/payouts/validations/__bank_det_valid.py
cashfree_sdk/payouts/validations/__bulk_bank_validation.py
cashfree_sdk/payouts/validations/__get_bulk_bank_valid_status.py
cashfree_sdk/payouts/validations/__init__.py
cashfree_sdk/payouts/validations/__upi_validation.py