Metadata-Version: 2.1
Name: cashfree-sdk
Version: 0.1.2
Summary: Library to integrate cashfree APIs
Home-page: https://github.com/cashfree/cashfree-sdk-python
Author: Cashfree
Author-email: ankur@cashfree.com
License: MIT
Download-URL: https://github.com/cashfree/cashfree-sdk-python/archive/0.1.2.tar.gz
Platform: UNKNOWN
Requires-Python: >=3.5
